AUTHORS
Changelog
LICENSE
MANIFEST.in
README.md
TODO
setup.cfg
setup.py
doc/INSTALL
doc/INSTALL.rus.txt
doc/README.rus.txt
doc/WEBFRAMEWORKS.rus.txt
doc/examples/dt.distance_of_time_in_words.py
doc/examples/dt.ru_strftime.py
doc/examples/numeral.choose_plural.py
doc/examples/numeral.in_words.py
doc/examples/numeral.rubles.py
doc/examples/numeral.sum_string.py
doc/examples/test.py
doc/examples/translit.py
doc/examples-django/README
doc/examples-django/pytilsex/__init__.py
doc/examples-django/pytilsex/manage.py
doc/examples-django/pytilsex/settings.py
doc/examples-django/pytilsex/tests.py
doc/examples-django/pytilsex/urls.py
doc/examples-django/pytilsex/static/css/style.css
doc/examples-django/pytilsex/static/images/header_inner.png
doc/examples-django/pytilsex/templates/base.html
doc/examples-django/pytilsex/templates/dt.html
doc/examples-django/pytilsex/templates/numeral.html
doc/examples-django/pytilsex/templates/translit.html
pytils/__init__.py
pytils/dt.py
pytils/numeral.py
pytils/translit.py
pytils/typo.py
pytils/utils.py
pytils/templatetags/__init__.py
pytils/templatetags/pytils_dt.py
pytils/templatetags/pytils_numeral.py
pytils/templatetags/pytils_translit.py
pytils/test/__init__.py
pytils/test/test_dt.py
pytils/test/test_numeral.py
pytils/test/test_translit.py
pytils/test/test_typo.py
pytils/test/test_utils.py
pytils/test/templatetags/__init__.py
pytils/test/templatetags/helpers.py
pytils/test/templatetags/test_common.py
pytils/test/templatetags/test_dt.py
pytils/test/templatetags/test_numeral.py
pytils/test/templatetags/test_translit.py
pytils/third/__init__.py
pytils/third/six.py
pytils_safe.egg-info/PKG-INFO
pytils_safe.egg-info/SOURCES.txt
pytils_safe.egg-info/dependency_links.txt
pytils_safe.egg-info/top_level.txt
pytils_safe.egg-info/zip-safe