Metadata-Version: 1.1
Name: pytils-safe
Version: 0.3.2
Summary: Russian-specific string utils
Home-page: https://github.com/j2a/pytils/
Author: Yury Yurevich
Author-email: yyurevich@jellycrystal.com
License: MIT
Platform: All
Classifier: Topic :: Software Development :: Libraries :: Python Modules
Classifier: Topic :: Text Processing :: Linguistic
Classifier: License :: OSI Approved :: MIT License
Classifier: Operating System :: OS Independent
Classifier: Programming Language :: Python
Classifier: Programming Language :: Python :: 2
Classifier: Programming Language :: Python :: 2.7
Classifier: Programming Language :: Python :: 3
Classifier: Programming Language :: Python :: 3.6
Classifier: Programming Language :: Python :: 3.7
Classifier: Natural Language :: Russian
Classifier: Development Status :: 4 - Beta
Classifier: Intended Audience :: Developers
